setup.py
gauss_bin_probability/Binomialdistribution.py
gauss_bin_probability/Gaussiandistribution.py
gauss_bin_probability/Generaldistribution.py
gauss_bin_probability/__init__.py
gauss_bin_probability.egg-info/PKG-INFO
gauss_bin_probability.egg-info/SOURCES.txt
gauss_bin_probability.egg-info/dependency_links.txt
gauss_bin_probability.egg-info/not-zip-safe
gauss_bin_probability.egg-info/top_level.txt