Metadata-Version: 1.0
Name: gauss-bin-probability
Version: 0.1
Summary: Gaussian and binomial distributions
Home-page: UNKNOWN
Author: Kumar Sanu
Author-email: krsanurajput@outlook.com
License: UNKNOWN
Platform: UNKNOWN
